{"date":"Tue, 20 Jun 2017 10:25:17 GMT","content-type":"image/jpeg","content-length":"12045","connection":"close","set-cookie":["__cfduid=dfcb9d85fe586d55319ede897ccea7c931497954317; expires=Wed, 20-Jun-18 10:25:17 GMT; path=/; domain=.tmdb.org; HttpOnly"],"access-control-allow-origin":"*","cache-control":"public, max-age=31449600","cf-bgj":"imgq:85","cf-polished":"degrade=85, origSize=27589","etag":"\"0180bae07d4ae5c536e9307914f40a5d\"","expires":"Tue, 19 Jun 2018 10:25:17 GMT","last-modified":"Tue, 13 Jun 2017 00:56:07 GMT","x-content-digest":"a8fe01877909d372ac8f95e7723fc9ed37ab91ff","x-rack-cache":"fresh","cf-cache-status":"HIT","accept-ranges":"bytes","server":"cloudflare-nginx","cf-ray":"371e05f62f9c1571-CDG"}