{"date":"Tue, 20 Jun 2017 10:26:40 GMT","content-type":"image/jpeg","content-length":"15937","connection":"close","set-cookie":["__cfduid=dd1927a0aa0c36d77c87e1115e47853091497954400; expires=Wed, 20-Jun-18 10:26:40 GMT; path=/; domain=.tmdb.org; HttpOnly"],"access-control-allow-origin":"*","cache-control":"public, max-age=31449600","cf-bgj":"imgq:85","cf-polished":"degrade=85, origSize=27695","etag":"\"6e3ad99173620092f04aa0d1fa671029\"","expires":"Tue, 19 Jun 2018 10:26:40 GMT","last-modified":"Fri, 10 Feb 2017 13:57:24 GMT","x-content-digest":"5b50c1c922f75e9974f25515250f9956c4d75f0c","x-rack-cache":"fresh","cf-cache-status":"HIT","accept-ranges":"bytes","server":"cloudflare-nginx","cf-ray":"371e07fa5af91061-CDG"}