{"date":"Tue, 20 Jun 2017 10:27:08 GMT","content-type":"image/jpeg","content-length":"15469","connection":"close","set-cookie":["__cfduid=d57f8273438ea5d7d0ebadc940841a9df1497954428; expires=Wed, 20-Jun-18 10:27:08 GMT; path=/; domain=.tmdb.org; HttpOnly"],"access-control-allow-origin":"*","cache-control":"public, max-age=31449600","cf-bgj":"imgq:85","cf-polished":"degrade=85, origSize=51798","etag":"\"5fa0a3b1b7737db3a3cb9819782e400d\"","expires":"Tue, 19 Jun 2018 10:27:08 GMT","last-modified":"Tue, 14 Mar 2017 21:35:56 GMT","x-content-digest":"8f57e4020e869f2299351fe525ecdca0590854ea","x-rack-cache":"fresh","cf-cache-status":"HIT","accept-ranges":"bytes","server":"cloudflare-nginx","cf-ray":"371e08a7ce9a14f7-CDG"}