{"date":"Tue, 20 Jun 2017 10:21:54 GMT","content-type":"image/jpeg","content-length":"8738","connection":"close","set-cookie":["__cfduid=d42fa4c3303713dbda139107cce3e290b1497954114; expires=Wed, 20-Jun-18 10:21:54 GMT; path=/; domain=.tmdb.org; HttpOnly"],"access-control-allow-origin":"*","cache-control":"public, max-age=31449600","etag":"\"80e4bdc1f8d5f0ca5b92641d8100a6bf\"","expires":"Tue, 19 Jun 2018 10:21:54 GMT","last-modified":"Mon, 13 Mar 2017 06:15:45 GMT","x-content-digest":"eff23acee6e8d22f2dadf1d4507f17189a1652b8","x-rack-cache":"fresh","cf-cache-status":"MISS","accept-ranges":"bytes","server":"cloudflare-nginx","cf-ray":"371e00fca8f90902-CDG"}