{"access-control-allow-origin":"*","access-control-expose-headers":"ETag, X-RateLimit-Limit, X-RateLimit-Remaining, X-RateLimit-Reset, Retry-After","cache-control":"public, max-age=28800","content-type":"application/json;charset=utf-8","date":"Tue, 20 Jun 2017 10:22:39 GMT","etag":"\"fbdf6ebcbebb632b730bb1c3de019cb1\"","server":"openresty","vary":"Accept-Encoding","x-memc":"HIT","x-memc-age":"15178","x-memc-expires":"13622","x-memc-key":"9e8eab766fc21a8bca6154216d4d94bd","x-ratelimit-limit":"40","x-ratelimit-remaining":"38","x-ratelimit-reset":"1497954169","content-length":"23836","connection":"Close"}