{"date":"Tue, 20 Jun 2017 10:21:53 GMT","content-type":"image/jpeg","content-length":"8234","connection":"close","set-cookie":["__cfduid=dd53a449594642aa5c805c294bebd26bf1497954113; expires=Wed, 20-Jun-18 10:21:53 GMT; path=/; domain=.tmdb.org; HttpOnly"],"access-control-allow-origin":"*","cache-control":"public, max-age=31449600","cf-bgj":"imgq:85","cf-polished":"degrade=85, origSize=14145","etag":"\"c6cf0734fd66afe09ef598224004c1bf\"","expires":"Tue, 19 Jun 2018 10:21:53 GMT","last-modified":"Sat, 11 Mar 2017 20:02:33 GMT","x-content-digest":"b535f8d115cb79ae314f7d0181aa7cdc401ca7d2","x-rack-cache":"fresh","cf-cache-status":"HIT","accept-ranges":"bytes","server":"cloudflare-nginx","cf-ray":"371e00fbee7214fd-CDG"}