{"date":"Tue, 20 Jun 2017 10:21:18 GMT","content-type":"image/jpeg","content-length":"8788","connection":"close","set-cookie":["__cfduid=dbdff005e63c8f9ac0468c86cb2fe460f1497954078; expires=Wed, 20-Jun-18 10:21:18 GMT; path=/; domain=.tmdb.org; HttpOnly"],"access-control-allow-origin":"*","cache-control":"public, max-age=31449600","cf-bgj":"imgq:85","cf-polished":"degrade=85, origSize=17073","etag":"\"eda0a00d495c970df66da1c508f221d3\"","expires":"Tue, 19 Jun 2018 10:21:18 GMT","last-modified":"Thu, 16 Feb 2017 04:49:57 GMT","x-content-digest":"d56fedcb97feb6c078b1a45fa042ea23715a6e21","x-rack-cache":"fresh","cf-cache-status":"HIT","accept-ranges":"bytes","server":"cloudflare-nginx","cf-ray":"371e0021bd3c14df-CDG"}