{"date":"Tue, 20 Jun 2017 10:21:42 GMT","content-type":"image/jpeg","content-length":"6367","connection":"close","set-cookie":["__cfduid=d4b2ccbcb0a5b9586173312201d4746b51497954102; expires=Wed, 20-Jun-18 10:21:42 GMT; path=/; domain=.tmdb.org; HttpOnly"],"access-control-allow-origin":"*","cache-control":"public, max-age=31449600","etag":"\"ea3b4e2d4489c5acb13669cd1a19393c\"","expires":"Tue, 19 Jun 2018 10:21:42 GMT","last-modified":"Mon, 13 Feb 2017 23:00:25 GMT","x-content-digest":"f2e93f1dc417ebe829faae285def4dda93d67b4e","x-rack-cache":"fresh","cf-cache-status":"HIT","accept-ranges":"bytes","server":"cloudflare-nginx","cf-ray":"371e00b63ee53c11-CDG"}