{"date":"Tue, 20 Jun 2017 10:28:01 GMT","content-type":"image/jpeg","content-length":"14945","connection":"close","set-cookie":["__cfduid=df2d3e85b451bf534cf6b80c0bb2c20471497954481; expires=Wed, 20-Jun-18 10:28:01 GMT; path=/; domain=.tmdb.org; HttpOnly"],"access-control-allow-origin":"*","cache-control":"public, max-age=31449600","cf-bgj":"imgq:85","cf-polished":"degrade=85, origSize=34093","etag":"\"d2e2f6fec5c1cec8a9dfc0444383d1a4\"","expires":"Tue, 19 Jun 2018 10:28:01 GMT","last-modified":"Wed, 15 Mar 2017 20:51:07 GMT","x-content-digest":"e5c845dabfd00fa922305dc57f07d6ca8e5027e8","x-rack-cache":"fresh","cf-cache-status":"HIT","accept-ranges":"bytes","server":"cloudflare-nginx","cf-ray":"371e09f67d0369a6-CDG"}