{"date":"Tue, 20 Jun 2017 10:21:38 GMT","content-type":"image/jpeg","content-length":"6968","connection":"close","set-cookie":["__cfduid=d744ac00be2c659993e82a57748618fed1497954098; expires=Wed, 20-Jun-18 10:21:38 GMT; path=/; domain=.tmdb.org; HttpOnly"],"access-control-allow-origin":"*","cache-control":"public, max-age=31449600","cf-bgj":"imgq:85","cf-polished":"degrade=85, origSize=35448","etag":"\"7c372cb272b8e3ff825f54c2abeb1f16\"","expires":"Tue, 19 Jun 2018 10:21:38 GMT","last-modified":"Sat, 10 Dec 2016 15:25:36 GMT","x-content-digest":"a18ac79976a9376a3d511ed7d37da71d439208a1","x-rack-cache":"fresh","cf-cache-status":"HIT","accept-ranges":"bytes","server":"cloudflare-nginx","cf-ray":"371e009e3bae3c77-CDG"}