{"date":"Tue, 20 Jun 2017 10:23:10 GMT","content-type":"image/jpeg","content-length":"7835","connection":"close","set-cookie":["__cfduid=ddee7584a7463a10db9564a09d41b2f071497954189; expires=Wed, 20-Jun-18 10:23:09 GMT; path=/; domain=.tmdb.org; HttpOnly"],"access-control-allow-origin":"*","cache-control":"public, max-age=31449600","etag":"\"235d340da4ce2ede891d2f93749af9bf\"","expires":"Tue, 19 Jun 2018 10:23:10 GMT","last-modified":"Fri, 07 Apr 2017 10:27:10 GMT","x-content-digest":"014e049ce3907a1698bb44f165a114137afb8f97","x-rack-cache":"stale, valid, store","cf-cache-status":"MISS","accept-ranges":"bytes","server":"cloudflare-nginx","cf-ray":"371e02d65bc43c77-CDG"}