{"date":"Tue, 20 Jun 2017 10:21:51 GMT","content-type":"image/jpeg","content-length":"7931","connection":"close","set-cookie":["__cfduid=d24bccabeec67041791140e3510f27ccb1497954111; expires=Wed, 20-Jun-18 10:21:51 GMT; path=/; domain=.tmdb.org; HttpOnly"],"access-control-allow-origin":"*","cache-control":"public, max-age=31449600","etag":"\"e1db3d8a8470a89e8f183875dee1f4cc\"","expires":"Tue, 19 Jun 2018 10:21:51 GMT","last-modified":"Thu, 16 Mar 2017 22:04:25 GMT","x-content-digest":"27182bca36c996270b83b4b03c06b32e9cfb08fc","x-rack-cache":"fresh","cf-cache-status":"HIT","accept-ranges":"bytes","server":"cloudflare-nginx","cf-ray":"371e00eb880d690e-CDG"}